{"problem": {"auth": 1, "author": "LingNc", "isRemote": false, "problemId": "C1045", "description": "编写一个程序，从键盘输入8个整数到数组中，然后对数组进行从小到大排序，并输出排序后的数组。", "source": "C程序设计A-机试题库", "title": "45.数组排序", "input": "输入8个整数，以空格分隔。", "output": "输出排序后的8个整数，以空格分隔。", "examples": "<input>3 1 4 1 5 9 2 6</input><output>1 1 2 3 4 5 6 9</output>", "difficulty": 1, "ioScore": 100, "codeShare": true, "hint": "$ 数据范围: \n -10^9 \\leq 数组元素 \\leq 10^9 $", "type": 1, "timeLimit": 1000, "memoryLimit": 256, "stackLimit": 128, "isRemoveEndBlank": true, "openCaseResult": true, "judgeCaseMode": "default", "isFileIO": false, "isGroup": false, "isUploadCase": true, "judgeMode": "default"}, "judgeMode": "default", "samples": [{"input": "1.in", "output": "1.out", "score": 50}, {"input": "2.in", "output": "2.out", "score": 20}, {"input": "3.in", "output": "3.out", "score": 10}, {"input": "4.in", "output": "4.out", "score": 10}, {"input": "5.in", "output": "5.out", "score": 10}], "tags": ["河工C语言上机题库A"], "codeTemplates": [], "languages": ["C", "C With O2", "C++", "C++ With O2", "C++ 17", "C++ 17 With O2", "C++ 20", "C++ 20 With O2", "Java", "Python3", "Golang", "C#", "JavaScript Node", "JavaScript V8"]}