{"problem": {"auth": 1, "author": "LingNc", "isRemote": false, "problemId": "C1010", "description": "编写一个程序，求解1到1000之间满足以下条件的所有整数：\n- 除以3余1\n- 除以5余2\n- 除以7余3。\n输出所有满足条件的整数。", "source": "C程序设计A-机试题库", "title": "10.特殊整数求解", "type": 1, "timeLimit": 1000, "memoryLimit": 256, "stackLimit": 128, "input": "无输入", "output": "输出所有满足条件的整数，每个整数占一行。", "examples": "<input></input><output>17\n52\n87\n...</output>", "difficulty": 1, "ioScore": 100, "codeShare": true, "hint": "", "isRemoveEndBlank": true, "openCaseResult": true, "judgeCaseMode": "default", "isFileIO": false, "isGroup": false, "isUploadCase": true, "judgeMode": "default"}, "judgeMode": "default", "samples": [{"input": "1.in", "output": "1.out", "score": 100}], "tags": ["河工C语言上机题库A"], "codeTemplates": [], "languages": ["C", "C With O2", "C++", "C++ With O2", "C++ 17", "C++ 17 With O2", "C++ 20", "C++ 20 With O2", "Java", "Python3", "Golang", "C#", "JavaScript Node", "JavaScript V8"]}